avogadr_py/__init__.py
avogadr_py/__main__.py
avogadr_py-1.0.1.dist-info/LICENSE
avogadr_py-1.0.1.dist-info/METADATA
avogadr_py-1.0.1.dist-info/WHEEL
avogadr_py-1.0.1.dist-info/entry_points.txt
avogadr_py-1.0.1.dist-info/top_level.txt
avogadr_py-1.0.1.dist-info/RECORD
